tlse2109.cpython-311-x86_64-linux-gnu.so
tlse2109-0.1.0.dist-info/top_level.txt
tlse2109-0.1.0.dist-info/METADATA
tlse2109-0.1.0.dist-info/LICENSE
tlse2109-0.1.0.dist-info/WHEEL
tlse2109-0.1.0.dist-info/RECORD
